{
  "code": "000",
  "data": {
    "columnMetas": [
      {
        "isNullable": 1,
        "displaySize": 19,
        "label": "PRICE",
        "name": "PRICE",
        "schemaName": "DEFAULT",
        "catelogName": null,
        "tableName": "KYLIN_SALES",
        "precision": 19,
        "scale": 4,
        "columnType": 3,
        "columnTypeName": "DECIMAL",
        "readOnly": true,
        "autoIncrement": false,
        "caseSensitive": true,
        "searchable": false,
        "currency": false,
        "signed": true,
        "definitelyWritable": false,
        "writable": false
      }
    ],
    "results": [
      [
        "99.9908"
      ]
    ],
    "cube": "INVERTED_INDEX[name=kylin_sales_cube]",
    "affectedRowCount": 0,
    "isException": false,
    "exceptionMessage": null,
    "pushDown": false,
    "partial": false,
    "traceUrl": null,
    "suiteId": null
  },
  "msg": ""
}
